<annotation>
	<folder>ManualScreenshotDataset</folder>
	<filename>gmail-message.png</filename>
	<path>/home/waltteri/Asiakirjat/Opiskelu/Master's Thesis/Python/ManualScreenshotDataset/gmail-message.png</path>
	<source>
		<database>Unknown</database>
	</source>
	<size>
		<width>1024</width>
		<height>866</height>
		<depth>3</depth>
	</size>
	<segmented>0</segmented>
	<object>
		<name>header</name>
		<pose>Unspecified</pose>
		<truncated>0</truncated>
		<difficult>0</difficult>
		<bndbox>
			<xmin>74</xmin>
			<ymin>11</ymin>
			<xmax>222</xmax>
			<ymax>48</ymax>
		</bndbox>
	</object>
	<object>
		<name>button</name>
		<pose>Unspecified</pose>
		<truncated>0</truncated>
		<difficult>0</difficult>
		<bndbox>
			<xmin>809</xmin>
			<ymin>15</ymin>
			<xmax>835</xmax>
			<ymax>43</ymax>
		</bndbox>
	</object>
	<object>
		<name>button</name>
		<pose>Unspecified</pose>
		<truncated>0</truncated>
		<difficult>0</difficult>
		<bndbox>
			<xmin>836</xmin>
			<ymin>15</ymin>
			<xmax>869</xmax>
			<ymax>43</ymax>
		</bndbox>
	</object>
	<object>
		<name>button</name>
		<pose>Unspecified</pose>
		<truncated>0</truncated>
		<difficult>0</difficult>
		<bndbox>
			<xmin>869</xmin>
			<ymin>16</ymin>
			<xmax>903</xmax>
			<ymax>45</ymax>
		</bndbox>
	</object>
	<object>
		<name>container</name>
		<pose>Unspecified</pose>
		<truncated>1</truncated>
		<difficult>0</difficult>
		<bndbox>
			<xmin>59</xmin>
			<ymin>1</ymin>
			<xmax>920</xmax>
			<ymax>56</ymax>
		</bndbox>
	</object>
	<object>
		<name>text-input</name>
		<pose>Unspecified</pose>
		<truncated>0</truncated>
		<difficult>0</difficult>
		<bndbox>
			<xmin>63</xmin>
			<ymin>57</ymin>
			<xmax>918</xmax>
			<ymax>107</ymax>
		</bndbox>
	</object>
	<object>
		<name>text-input</name>
		<pose>Unspecified</pose>
		<truncated>0</truncated>
		<difficult>0</difficult>
		<bndbox>
			<xmin>62</xmin>
			<ymin>108</ymin>
			<xmax>919</xmax>
			<ymax>160</ymax>
		</bndbox>
	</object>
	<object>
		<name>common</name>
		<pose>Unspecified</pose>
		<truncated>0</truncated>
		<difficult>0</difficult>
		<bndbox>
			<xmin>78</xmin>
			<ymin>171</ymin>
			<xmax>238</xmax>
			<ymax>200</ymax>
		</bndbox>
	</object>
	<object>
		<name>table-cell</name>
		<pose>Unspecified</pose>
		<truncated>0</truncated>
		<difficult>0</difficult>
		<bndbox>
			<xmin>81</xmin>
			<ymin>202</ymin>
			<xmax>266</xmax>
			<ymax>241</ymax>
		</bndbox>
	</object>
	<object>
		<name>table-cell</name>
		<pose>Unspecified</pose>
		<truncated>0</truncated>
		<difficult>0</difficult>
		<bndbox>
			<xmin>265</xmin>
			<ymin>201</ymin>
			<xmax>449</xmax>
			<ymax>242</ymax>
		</bndbox>
	</object>
	<object>
		<name>table-cell</name>
		<pose>Unspecified</pose>
		<truncated>0</truncated>
		<difficult>0</difficult>
		<bndbox>
			<xmin>449</xmin>
			<ymin>200</ymin>
			<xmax>632</xmax>
			<ymax>242</ymax>
		</bndbox>
	</object>
	<object>
		<name>table-cell</name>
		<pose>Unspecified</pose>
		<truncated>0</truncated>
		<difficult>0</difficult>
		<bndbox>
			<xmin>81</xmin>
			<ymin>242</ymin>
			<xmax>264</xmax>
			<ymax>282</ymax>
		</bndbox>
	</object>
	<object>
		<name>table-cell</name>
		<pose>Unspecified</pose>
		<truncated>0</truncated>
		<difficult>0</difficult>
		<bndbox>
			<xmin>263</xmin>
			<ymin>242</ymin>
			<xmax>451</xmax>
			<ymax>282</ymax>
		</bndbox>
	</object>
	<object>
		<name>table-cell</name>
		<pose>Unspecified</pose>
		<truncated>0</truncated>
		<difficult>0</difficult>
		<bndbox>
			<xmin>446</xmin>
			<ymin>241</ymin>
			<xmax>633</xmax>
			<ymax>282</ymax>
		</bndbox>
	</object>
	<object>
		<name>table-cell</name>
		<pose>Unspecified</pose>
		<truncated>0</truncated>
		<difficult>0</difficult>
		<bndbox>
			<xmin>81</xmin>
			<ymin>281</ymin>
			<xmax>265</xmax>
			<ymax>324</ymax>
		</bndbox>
	</object>
	<object>
		<name>table-cell</name>
		<pose>Unspecified</pose>
		<truncated>0</truncated>
		<difficult>0</difficult>
		<bndbox>
			<xmin>264</xmin>
			<ymin>281</ymin>
			<xmax>449</xmax>
			<ymax>323</ymax>
		</bndbox>
	</object>
	<object>
		<name>table-cell</name>
		<pose>Unspecified</pose>
		<truncated>0</truncated>
		<difficult>0</difficult>
		<bndbox>
			<xmin>447</xmin>
			<ymin>281</ymin>
			<xmax>635</xmax>
			<ymax>323</ymax>
		</bndbox>
	</object>
	<object>
		<name>table-cell</name>
		<pose>Unspecified</pose>
		<truncated>0</truncated>
		<difficult>0</difficult>
		<bndbox>
			<xmin>81</xmin>
			<ymin>323</ymin>
			<xmax>265</xmax>
			<ymax>364</ymax>
		</bndbox>
	</object>
	<object>
		<name>table-cell</name>
		<pose>Unspecified</pose>
		<truncated>0</truncated>
		<difficult>0</difficult>
		<bndbox>
			<xmin>264</xmin>
			<ymin>322</ymin>
			<xmax>449</xmax>
			<ymax>363</ymax>
		</bndbox>
	</object>
	<object>
		<name>table-cell</name>
		<pose>Unspecified</pose>
		<truncated>0</truncated>
		<difficult>0</difficult>
		<bndbox>
			<xmin>447</xmin>
			<ymin>322</ymin>
			<xmax>633</xmax>
			<ymax>365</ymax>
		</bndbox>
	</object>
	<object>
		<name>table-row</name>
		<pose>Unspecified</pose>
		<truncated>0</truncated>
		<difficult>0</difficult>
		<bndbox>
			<xmin>80</xmin>
			<ymin>202</ymin>
			<xmax>636</xmax>
			<ymax>243</ymax>
		</bndbox>
	</object>
	<object>
		<name>table-row</name>
		<pose>Unspecified</pose>
		<truncated>0</truncated>
		<difficult>0</difficult>
		<bndbox>
			<xmin>81</xmin>
			<ymin>241</ymin>
			<xmax>636</xmax>
			<ymax>283</ymax>
		</bndbox>
	</object>
	<object>
		<name>table-row</name>
		<pose>Unspecified</pose>
		<truncated>0</truncated>
		<difficult>0</difficult>
		<bndbox>
			<xmin>81</xmin>
			<ymin>282</ymin>
			<xmax>636</xmax>
			<ymax>325</ymax>
		</bndbox>
	</object>
	<object>
		<name>table-row</name>
		<pose>Unspecified</pose>
		<truncated>0</truncated>
		<difficult>0</difficult>
		<bndbox>
			<xmin>82</xmin>
			<ymin>322</ymin>
			<xmax>637</xmax>
			<ymax>366</ymax>
		</bndbox>
	</object>
	<object>
		<name>table</name>
		<pose>Unspecified</pose>
		<truncated>0</truncated>
		<difficult>0</difficult>
		<bndbox>
			<xmin>81</xmin>
			<ymin>202</ymin>
			<xmax>636</xmax>
			<ymax>368</ymax>
		</bndbox>
	</object>
	<object>
		<name>container</name>
		<pose>Unspecified</pose>
		<truncated>0</truncated>
		<difficult>0</difficult>
		<bndbox>
			<xmin>61</xmin>
			<ymin>161</ymin>
			<xmax>915</xmax>
			<ymax>720</ymax>
		</bndbox>
	</object>
	<object>
		<name>common</name>
		<pose>Unspecified</pose>
		<truncated>1</truncated>
		<difficult>0</difficult>
		<bndbox>
			<xmin>1</xmin>
			<ymin>22</ymin>
			<xmax>59</xmax>
			<ymax>74</ymax>
		</bndbox>
	</object>
	<object>
		<name>common</name>
		<pose>Unspecified</pose>
		<truncated>1</truncated>
		<difficult>0</difficult>
		<bndbox>
			<xmin>1</xmin>
			<ymin>76</ymin>
			<xmax>59</xmax>
			<ymax>133</ymax>
		</bndbox>
	</object>
	<object>
		<name>common</name>
		<pose>Unspecified</pose>
		<truncated>1</truncated>
		<difficult>0</difficult>
		<bndbox>
			<xmin>1</xmin>
			<ymin>136</ymin>
			<xmax>58</xmax>
			<ymax>190</ymax>
		</bndbox>
	</object>
	<object>
		<name>common</name>
		<pose>Unspecified</pose>
		<truncated>1</truncated>
		<difficult>0</difficult>
		<bndbox>
			<xmin>1</xmin>
			<ymin>192</ymin>
			<xmax>60</xmax>
			<ymax>249</ymax>
		</bndbox>
	</object>
	<object>
		<name>common</name>
		<pose>Unspecified</pose>
		<truncated>1</truncated>
		<difficult>0</difficult>
		<bndbox>
			<xmin>1</xmin>
			<ymin>249</ymin>
			<xmax>59</xmax>
			<ymax>305</ymax>
		</bndbox>
	</object>
	<object>
		<name>common</name>
		<pose>Unspecified</pose>
		<truncated>1</truncated>
		<difficult>0</difficult>
		<bndbox>
			<xmin>1</xmin>
			<ymin>305</ymin>
			<xmax>59</xmax>
			<ymax>364</ymax>
		</bndbox>
	</object>
	<object>
		<name>common</name>
		<pose>Unspecified</pose>
		<truncated>1</truncated>
		<difficult>0</difficult>
		<bndbox>
			<xmin>1</xmin>
			<ymin>364</ymin>
			<xmax>61</xmax>
			<ymax>424</ymax>
		</bndbox>
	</object>
	<object>
		<name>common</name>
		<pose>Unspecified</pose>
		<truncated>1</truncated>
		<difficult>0</difficult>
		<bndbox>
			<xmin>1</xmin>
			<ymin>425</ymin>
			<xmax>61</xmax>
			<ymax>478</ymax>
		</bndbox>
	</object>
	<object>
		<name>common</name>
		<pose>Unspecified</pose>
		<truncated>1</truncated>
		<difficult>0</difficult>
		<bndbox>
			<xmin>1</xmin>
			<ymin>478</ymin>
			<xmax>62</xmax>
			<ymax>536</ymax>
		</bndbox>
	</object>
	<object>
		<name>common</name>
		<pose>Unspecified</pose>
		<truncated>1</truncated>
		<difficult>0</difficult>
		<bndbox>
			<xmin>1</xmin>
			<ymin>536</ymin>
			<xmax>62</xmax>
			<ymax>593</ymax>
		</bndbox>
	</object>
	<object>
		<name>common</name>
		<pose>Unspecified</pose>
		<truncated>1</truncated>
		<difficult>0</difficult>
		<bndbox>
			<xmin>1</xmin>
			<ymin>595</ymin>
			<xmax>60</xmax>
			<ymax>649</ymax>
		</bndbox>
	</object>
	<object>
		<name>common</name>
		<pose>Unspecified</pose>
		<truncated>1</truncated>
		<difficult>0</difficult>
		<bndbox>
			<xmin>1</xmin>
			<ymin>649</ymin>
			<xmax>62</xmax>
			<ymax>708</ymax>
		</bndbox>
	</object>
	<object>
		<name>common</name>
		<pose>Unspecified</pose>
		<truncated>1</truncated>
		<difficult>0</difficult>
		<bndbox>
			<xmin>1</xmin>
			<ymin>708</ymin>
			<xmax>59</xmax>
			<ymax>768</ymax>
		</bndbox>
	</object>
	<object>
		<name>common</name>
		<pose>Unspecified</pose>
		<truncated>1</truncated>
		<difficult>0</difficult>
		<bndbox>
			<xmin>1</xmin>
			<ymin>769</ymin>
			<xmax>59</xmax>
			<ymax>823</ymax>
		</bndbox>
	</object>
	<object>
		<name>common</name>
		<pose>Unspecified</pose>
		<truncated>1</truncated>
		<difficult>0</difficult>
		<bndbox>
			<xmin>1</xmin>
			<ymin>824</ymin>
			<xmax>59</xmax>
			<ymax>866</ymax>
		</bndbox>
	</object>
	<object>
		<name>common</name>
		<pose>Unspecified</pose>
		<truncated>0</truncated>
		<difficult>0</difficult>
		<bndbox>
			<xmin>83</xmin>
			<ymin>725</ymin>
			<xmax>200</xmax>
			<ymax>769</ymax>
		</bndbox>
	</object>
	<object>
		<name>button</name>
		<pose>Unspecified</pose>
		<truncated>0</truncated>
		<difficult>0</difficult>
		<bndbox>
			<xmin>201</xmin>
			<ymin>728</ymin>
			<xmax>232</xmax>
			<ymax>769</ymax>
		</bndbox>
	</object>
	<object>
		<name>container</name>
		<pose>Unspecified</pose>
		<truncated>0</truncated>
		<difficult>0</difficult>
		<bndbox>
			<xmin>83</xmin>
			<ymin>720</ymin>
			<xmax>237</xmax>
			<ymax>772</ymax>
		</bndbox>
	</object>
	<object>
		<name>button</name>
		<pose>Unspecified</pose>
		<truncated>0</truncated>
		<difficult>0</difficult>
		<bndbox>
			<xmin>240</xmin>
			<ymin>724</ymin>
			<xmax>299</xmax>
			<ymax>770</ymax>
		</bndbox>
	</object>
	<object>
		<name>button</name>
		<pose>Unspecified</pose>
		<truncated>0</truncated>
		<difficult>0</difficult>
		<bndbox>
			<xmin>306</xmin>
			<ymin>725</ymin>
			<xmax>350</xmax>
			<ymax>771</ymax>
		</bndbox>
	</object>
	<object>
		<name>container</name>
		<pose>Unspecified</pose>
		<truncated>0</truncated>
		<difficult>0</difficult>
		<bndbox>
			<xmin>81</xmin>
			<ymin>722</ymin>
			<xmax>302</xmax>
			<ymax>774</ymax>
		</bndbox>
	</object>
	<object>
		<name>button</name>
		<pose>Unspecified</pose>
		<truncated>0</truncated>
		<difficult>0</difficult>
		<bndbox>
			<xmin>354</xmin>
			<ymin>724</ymin>
			<xmax>397</xmax>
			<ymax>770</ymax>
		</bndbox>
	</object>
	<object>
		<name>button</name>
		<pose>Unspecified</pose>
		<truncated>0</truncated>
		<difficult>0</difficult>
		<bndbox>
			<xmin>397</xmin>
			<ymin>722</ymin>
			<xmax>442</xmax>
			<ymax>770</ymax>
		</bndbox>
	</object>
	<object>
		<name>button</name>
		<pose>Unspecified</pose>
		<truncated>0</truncated>
		<difficult>0</difficult>
		<bndbox>
			<xmin>442</xmin>
			<ymin>726</ymin>
			<xmax>506</xmax>
			<ymax>767</ymax>
		</bndbox>
	</object>
	<object>
		<name>container</name>
		<pose>Unspecified</pose>
		<truncated>0</truncated>
		<difficult>0</difficult>
		<bndbox>
			<xmin>303</xmin>
			<ymin>721</ymin>
			<xmax>509</xmax>
			<ymax>775</ymax>
		</bndbox>
	</object>
	<object>
		<name>button</name>
		<pose>Unspecified</pose>
		<truncated>0</truncated>
		<difficult>0</difficult>
		<bndbox>
			<xmin>513</xmin>
			<ymin>727</ymin>
			<xmax>576</xmax>
			<ymax>768</ymax>
		</bndbox>
	</object>
	<object>
		<name>button</name>
		<pose>Unspecified</pose>
		<truncated>0</truncated>
		<difficult>0</difficult>
		<bndbox>
			<xmin>578</xmin>
			<ymin>726</ymin>
			<xmax>623</xmax>
			<ymax>768</ymax>
		</bndbox>
	</object>
	<object>
		<name>button</name>
		<pose>Unspecified</pose>
		<truncated>0</truncated>
		<difficult>0</difficult>
		<bndbox>
			<xmin>625</xmin>
			<ymin>727</ymin>
			<xmax>671</xmax>
			<ymax>769</ymax>
		</bndbox>
	</object>
	<object>
		<name>button</name>
		<pose>Unspecified</pose>
		<truncated>0</truncated>
		<difficult>0</difficult>
		<bndbox>
			<xmin>670</xmin>
			<ymin>726</ymin>
			<xmax>715</xmax>
			<ymax>768</ymax>
		</bndbox>
	</object>
	<object>
		<name>button</name>
		<pose>Unspecified</pose>
		<truncated>0</truncated>
		<difficult>0</difficult>
		<bndbox>
			<xmin>716</xmin>
			<ymin>729</ymin>
			<xmax>755</xmax>
			<ymax>768</ymax>
		</bndbox>
	</object>
	<object>
		<name>button</name>
		<pose>Unspecified</pose>
		<truncated>0</truncated>
		<difficult>0</difficult>
		<bndbox>
			<xmin>756</xmin>
			<ymin>725</ymin>
			<xmax>809</xmax>
			<ymax>769</ymax>
		</bndbox>
	</object>
	<object>
		<name>container</name>
		<pose>Unspecified</pose>
		<truncated>0</truncated>
		<difficult>0</difficult>
		<bndbox>
			<xmin>511</xmin>
			<ymin>724</ymin>
			<xmax>810</xmax>
			<ymax>773</ymax>
		</bndbox>
	</object>
	<object>
		<name>common</name>
		<pose>Unspecified</pose>
		<truncated>0</truncated>
		<difficult>0</difficult>
		<bndbox>
			<xmin>812</xmin>
			<ymin>727</ymin>
			<xmax>859</xmax>
			<ymax>771</ymax>
		</bndbox>
	</object>
	<object>
		<name>button</name>
		<pose>Unspecified</pose>
		<truncated>0</truncated>
		<difficult>0</difficult>
		<bndbox>
			<xmin>81</xmin>
			<ymin>797</ymin>
			<xmax>188</xmax>
			<ymax>854</ymax>
		</bndbox>
	</object>
	<object>
		<name>button</name>
		<pose>Unspecified</pose>
		<truncated>0</truncated>
		<difficult>0</difficult>
		<bndbox>
			<xmin>193</xmin>
			<ymin>802</ymin>
			<xmax>239</xmax>
			<ymax>847</ymax>
		</bndbox>
	</object>
	<object>
		<name>button</name>
		<pose>Unspecified</pose>
		<truncated>0</truncated>
		<difficult>0</difficult>
		<bndbox>
			<xmin>247</xmin>
			<ymin>805</ymin>
			<xmax>277</xmax>
			<ymax>843</ymax>
		</bndbox>
	</object>
	<object>
		<name>button</name>
		<pose>Unspecified</pose>
		<truncated>0</truncated>
		<difficult>0</difficult>
		<bndbox>
			<xmin>292</xmin>
			<ymin>806</ymin>
			<xmax>324</xmax>
			<ymax>840</ymax>
		</bndbox>
	</object>
	<object>
		<name>button</name>
		<pose>Unspecified</pose>
		<truncated>0</truncated>
		<difficult>0</difficult>
		<bndbox>
			<xmin>335</xmin>
			<ymin>806</ymin>
			<xmax>368</xmax>
			<ymax>842</ymax>
		</bndbox>
	</object>
	<object>
		<name>button</name>
		<pose>Unspecified</pose>
		<truncated>0</truncated>
		<difficult>0</difficult>
		<bndbox>
			<xmin>382</xmin>
			<ymin>809</ymin>
			<xmax>414</xmax>
			<ymax>840</ymax>
		</bndbox>
	</object>
	<object>
		<name>button</name>
		<pose>Unspecified</pose>
		<truncated>0</truncated>
		<difficult>0</difficult>
		<bndbox>
			<xmin>431</xmin>
			<ymin>809</ymin>
			<xmax>461</xmax>
			<ymax>841</ymax>
		</bndbox>
	</object>
	<object>
		<name>button</name>
		<pose>Unspecified</pose>
		<truncated>0</truncated>
		<difficult>0</difficult>
		<bndbox>
			<xmin>477</xmin>
			<ymin>809</ymin>
			<xmax>506</xmax>
			<ymax>842</ymax>
		</bndbox>
	</object>
	<object>
		<name>common</name>
		<pose>Unspecified</pose>
		<truncated>0</truncated>
		<difficult>0</difficult>
		<bndbox>
			<xmin>761</xmin>
			<ymin>812</ymin>
			<xmax>827</xmax>
			<ymax>842</ymax>
		</bndbox>
	</object>
	<object>
		<name>button</name>
		<pose>Unspecified</pose>
		<truncated>0</truncated>
		<difficult>0</difficult>
		<bndbox>
			<xmin>829</xmin>
			<ymin>808</ymin>
			<xmax>862</xmax>
			<ymax>845</ymax>
		</bndbox>
	</object>
	<object>
		<name>button</name>
		<pose>Unspecified</pose>
		<truncated>0</truncated>
		<difficult>0</difficult>
		<bndbox>
			<xmin>874</xmin>
			<ymin>805</ymin>
			<xmax>901</xmax>
			<ymax>844</ymax>
		</bndbox>
	</object>
	<object>
		<name>container</name>
		<pose>Unspecified</pose>
		<truncated>0</truncated>
		<difficult>0</difficult>
		<bndbox>
			<xmin>79</xmin>
			<ymin>722</ymin>
			<xmax>869</xmax>
			<ymax>777</ymax>
		</bndbox>
	</object>
	<object>
		<name>container</name>
		<pose>Unspecified</pose>
		<truncated>0</truncated>
		<difficult>0</difficult>
		<bndbox>
			<xmin>62</xmin>
			<ymin>719</ymin>
			<xmax>916</xmax>
			<ymax>865</ymax>
		</bndbox>
	</object>
	<object>
		<name>container</name>
		<pose>Unspecified</pose>
		<truncated>1</truncated>
		<difficult>0</difficult>
		<bndbox>
			<xmin>58</xmin>
			<ymin>1</ymin>
			<xmax>919</xmax>
			<ymax>866</ymax>
		</bndbox>
	</object>
	<object>
		<name>button</name>
		<pose>Unspecified</pose>
		<truncated>0</truncated>
		<difficult>0</difficult>
		<bndbox>
			<xmin>964</xmin>
			<ymin>769</ymin>
			<xmax>1022</xmax>
			<ymax>820</ymax>
		</bndbox>
	</object>
	<object>
		<name>button</name>
		<pose>Unspecified</pose>
		<truncated>1</truncated>
		<difficult>0</difficult>
		<bndbox>
			<xmin>918</xmin>
			<ymin>841</ymin>
			<xmax>954</xmax>
			<ymax>866</ymax>
		</bndbox>
	</object>
</annotation>
